{"1097263031458742272": {"balance": 8, "last_daily": "", "steals": [], "items": [], "boost_end": null}, "842120397192560650": {"balance": 10000000000000000000000100000000000, "last_daily": "2025-07-28T22:52:31.012055", "steals": ["2025-07-23", "2025-07-23", "2025-07-23"], "items": ["role_vip", "skin_slot", "ticket_loterie", "boost_x2", "emoji_special", "badge", "boost_x3"], "boost_end": "2025-07-26T02:05:18.092370"}, "1228651340729815063": {"balance": 55, "last_daily": "2025-07-22T15:43:52.772357", "steals": ["2025-07-23"], "items": [], "boost_end": null}, "1283590474396864605": {"balance": 600, "last_daily": "2025-07-24T12:55:53.150891", "steals": [], "items": [], "boost_end": null}}